{
  "url": "https://docs.jlinc.io/#/?id=the-jlinc-process",
  "domain": "docs.jlinc.io",
  "lastScraped": "2025-11-18T16:55:53.664Z",
  "totalPages": 1,
  "successfulPages": 1,
  "failedPages": [],
  "structure": [
    {
      "type": "JLINC Documentation Library",
      "url": "https://docs.jlinc.io/#/?id=the-jlinc-process"
    }
  ],
  "latestVersion": "1.0.0",
  "versions": [
    {
      "version": "1.0.0",
      "timestamp": "2025-11-18T16:55:53.664Z",
      "filename": "documentation_2025-11-18T16:55:53.664Z.md",
      "totalPages": 1,
      "successfulPages": 1,
      "url": "https://docs.jlinc.io/#/?id=the-jlinc-process",
      "isLatest": true,
      "label": "latest"
    }
  ],
  "schemaVersion": 2
}
