{
  "url": "https://rune.mallardorder.io",
  "domain": "rune.mallardorder.io",
  "lastScraped": "2025-09-30T12:24:13.068Z",
  "totalPages": 14,
  "successfulPages": 14,
  "failedPages": [],
  "structure": [
    {
      "type": "RUNE V2 intro | RUNE Ecosystem",
      "url": "https://rune.mallardorder.io"
    },
    {
      "type": "Tokenomics | RUNE Ecosystem",
      "url": "https://rune.mallardorder.io/getting-started/quickstart"
    },
    {
      "type": "Social Fi | RUNE Ecosystem",
      "url": "https://rune.mallardorder.io/getting-started/social-fi"
    },
    {
      "type": "Utility | RUNE Ecosystem",
      "url": "https://rune.mallardorder.io/getting-started/publish-your-docs"
    },
    {
      "type": "Disclaimer | RUNE Ecosystem",
      "url": "https://rune.mallardorder.io/disclaimer"
    },
    {
      "type": "Rewards | RUNE Ecosystem",
      "url": "https://rune.mallardorder.io/getting-started/rewards"
    },
    {
      "type": "Burn Pit | RUNE Ecosystem",
      "url": "https://rune.mallardorder.io/staking/burn-pit"
    },
    {
      "type": "Token Staking | RUNE Ecosystem",
      "url": "https://rune.mallardorder.io/staking/images-and-media"
    },
    {
      "type": "How it works | RUNE Ecosystem",
      "url": "https://rune.mallardorder.io/staking/markdown"
    },
    {
      "type": "Treasury | RUNE Ecosystem",
      "url": "https://rune.mallardorder.io/getting-started/editor"
    },
    {
      "type": "NFT Staking | RUNE Ecosystem",
      "url": "https://rune.mallardorder.io/staking/interactive-blocks"
    },
    {
      "type": "V1 to V2 conversion | RUNE Ecosystem",
      "url": "https://rune.mallardorder.io/staking/integrations"
    },
    {
      "type": "Tokenomics | RUNE Ecosystem",
      "url": "https://rune.mallardorder.io/getting-started"
    },
    {
      "type": "How it works | RUNE Ecosystem",
      "url": "https://rune.mallardorder.io/staking"
    }
  ],
  "latestVersion": "1.1.0",
  "versions": [
    {
      "version": "1.0.0",
      "timestamp": "2025-09-27T01:13:34.265Z",
      "filename": "documentation_2025-09-27T01:13:34.265Z.md",
      "totalPages": 14,
      "successfulPages": 14,
      "url": "https://rune.mallardorder.io",
      "isLatest": false
    },
    {
      "version": "1.1.0",
      "timestamp": "2025-09-30T12:24:13.068Z",
      "filename": "documentation_2025-09-30T12:24:13.068Z.md",
      "totalPages": 14,
      "successfulPages": 14,
      "url": "https://rune.mallardorder.io",
      "isLatest": true,
      "label": "latest"
    }
  ],
  "schemaVersion": 2
}
